yctl/__init__.py
yctl/control.py
yctl-1.0.0.dist-info/LICENSE
yctl-1.0.0.dist-info/METADATA
yctl-1.0.0.dist-info/WHEEL
yctl-1.0.0.dist-info/top_level.txt
yctl-1.0.0.dist-info/RECORD
