Metadata-Version: 2.1
Name: yctl
Version: 1.0.0
Summary: Query and control an Yggdrasil Network node with Admin API
Home-page: https://github.com/zhoreeq/yctl
Author: zhoreeq
Author-email: zhoreeq@protonmail.com
License: LGPL
Keywords: yggdrasil network mesh
Platform: UNKNOWN
Classifier: Development Status :: 5 - Production/Stable
Classifier: Intended Audience :: Developers
Classifier: Topic :: Communications
Classifier: License :: OSI Approved :: GNU Library or Lesser General Public License (LGPL)
Classifier: Programming Language :: Python :: 3
Requires-Python: >=3
License-File: LICENSE
